pysveasolar/__init__.py
pysveasolar/api.py
pysveasolar/auth.py
pysveasolar/errors.py
pysveasolar/models.py
pysveasolar/token_manager.py
pysveasolar/token_managers/filesystem.py
pysveasolar-0.1.2.dist-info/METADATA
pysveasolar-0.1.2.dist-info/WHEEL
pysveasolar-0.1.2.dist-info/RECORD
