Metadata-Version: 2.3
Name: pysveasolar
Version: 0.1.2
Summary: 
Author: Johan Nenzén
Author-email: johan.nanzen@gmail.com
Requires-Python: >=3.12,<4.0
Classifier: Programming Language :: Python :: 3
Classifier: Programming Language :: Python :: 3.12
Classifier: Programming Language :: Python :: 3.13
Requires-Dist: aiohttp (>=3.11.14,<4.0.0)
Requires-Dist: dataclass-wizard (>=0.35.0,<0.36.0)
Requires-Dist: poetry-core (>=2.1.2,<3.0.0)
Requires-Dist: pyjwt (>=2.8.0,<3.0.0)
